otter_grader_labextension/__init__.py
otter_grader_labextension/_version.py
otter_grader_labextension-0.1.1.data/data/share/jupyter/labextensions/otter-grader-labextension/package.json
otter_grader_labextension-0.1.1.data/data/share/jupyter/labextensions/otter-grader-labextension/schemas/otter-grader-labextension/package.json.orig
otter_grader_labextension-0.1.1.data/data/share/jupyter/labextensions/otter-grader-labextension/schemas/otter-grader-labextension/plugin.json
otter_grader_labextension-0.1.1.data/data/share/jupyter/labextensions/otter-grader-labextension/static/568.2ff1b5a29472376e8bc1.js
otter_grader_labextension-0.1.1.data/data/share/jupyter/labextensions/otter-grader-labextension/static/747.b388d16ae6ca3f003427.js
otter_grader_labextension-0.1.1.data/data/share/jupyter/labextensions/otter-grader-labextension/static/remoteEntry.281c82cfd4399734f74f.js
otter_grader_labextension-0.1.1.data/data/share/jupyter/labextensions/otter-grader-labextension/static/style.js
otter_grader_labextension-0.1.1.data/data/share/jupyter/labextensions/otter-grader-labextension/static/third-party-licenses.json
otter_grader_labextension-0.1.1.data/data/share/jupyter/labextensions/otter-grader-labextension/install.json
otter_grader_labextension-0.1.1.dist-info/METADATA
otter_grader_labextension-0.1.1.dist-info/WHEEL
otter_grader_labextension-0.1.1.dist-info/licenses/LICENSE
otter_grader_labextension-0.1.1.dist-info/RECORD
